README.rst
mousai/__init__.py
mousai/har_bal.py
mousai-0.3.1.dist-info/METADATA
mousai-0.3.1.dist-info/RECORD
mousai-0.3.1.dist-info/WHEEL
mousai-0.3.1.dist-info/top_level.txt
