Metadata-Version: 2.1
Name: mousai
Version: 0.3.1
Summary: Harmonic Balance solvers.
Home-page: https://josephcslater.github.io/mousai/
Author: Joseph C. Slater
Author-email: joseph.c.slater@gmail.com
License: UNKNOWN
Download-URL: https://github.com/josephcslater/mousai
Keywords: harmonic balance,numerical solvers,vibration,oscillation
Platform: UNKNOWN
Requires-Dist: numpy
Requires-Dist: scipy
Requires-Dist: matplotlib
